[
    {
        "id": "section-1948",
        "ja": "WHO憲章の土台",
        "vi": "Nền tảng Hiến chương WHO"
    },
    {
        "id": "sbo112-privacy-evolution",
        "ja": "医療プライバシーの進化",
        "vi": "Tiến hóa quyền riêng tư y tế"
    },
    {
        "id": "sbo122",
        "ja": "医療情報保護と情報開示",
        "vi": "Bảo vệ & công khai thông tin y tế"
    },
    {
        "id": "sbo123",
        "ja": "患者参画と共創の医療",
        "vi": "Sự tham gia của bệnh nhân & Đồng kiến tạo"
    },
    {
        "id": "sbo211",
        "ja": "社会保障制度",
        "vi": "Hệ thống an sinh xã hội"
    },
    {
        "id": "sbo212",
        "ja": "医療提供体制",
        "vi": "Hệ thống cung cấp y tế"
    },
    {
        "id": "sbo213",
        "ja": "医療保険制度",
        "vi": "Hệ thống bảo hiểm y tế"
    },
    {
        "id": "sbo214",
        "ja": "保険診療報酬",
        "vi": "Giá dịch vụ y tế bảo hiểm"
    },
    {
        "id": "sbo311",
        "ja": "解剖学 (Anatomy)",
        "vi": "Giải phẫu học (Anatomy)"
    },
    {
        "id": "sbo312",
        "ja": "生理学 (Physiology)",
        "vi": "Sinh lý học (Physiology)"
    },
    {
        "id": "sbo411",
        "ja": "臨床症候学",
        "vi": "Triệu chứng lâm sàng"
    },
    {
        "id": "sbo412",
        "ja": "臨床推論 (Clinical Reasoning)",
        "vi": "Suy luận lâm sàng (Clinical Reasoning)"
    }
]
